dlspark/__init__.py
dlspark/auto_grad.py
dlspark/data/__init__.py
dlspark/data/dataloader_basic.py
dlspark/data/transforms.py
dlspark/data/datasets/MNIST_dataset.py
dlspark/data/datasets/__init__.py
dlspark/data/datasets/dataset_basic.py
dlspark/init/__init__.py
dlspark/init/init_basic.py
dlspark/nn/__init__.py
dlspark/nn/activation.py
dlspark/nn/layers.py
dlspark/nn/loss.py
dlspark/nn/module.py
dlspark/nn/optimizer/Adam.py
dlspark/nn/optimizer/Optimizer.py
dlspark/nn/optimizer/SGD.py
dlspark/nn/optimizer/__init__.py
dlspark/ops/__init__.py
dlspark/ops/ops_activation.py
dlspark/ops/ops_basic.py
dlspark/ops/ops_cnn.py
dlspark/ops/ops_loss.py
dlspark-1.0.4.dist-info/LICENSE
dlspark-1.0.4.dist-info/METADATA
dlspark-1.0.4.dist-info/WHEEL
dlspark-1.0.4.dist-info/top_level.txt
dlspark-1.0.4.dist-info/RECORD
